beast_skygrid/__about__.py
beast_skygrid/__init__.py
beast_skygrid/__main__.py
beast_skygrid/snk.yaml
beast_skygrid/cli/__init__.py
beast_skygrid/workflow/Snakefile
beast_skygrid/workflow/utils.py
beast_skygrid/workflow/envs/beast.yaml
beast_skygrid/workflow/envs/ggtree.post-deploy.sh
beast_skygrid/workflow/envs/ggtree.yaml
beast_skygrid/workflow/envs/rttr.yaml
beast_skygrid/workflow/envs/seqkit.yaml
beast_skygrid/workflow/profiles/slurm/config.yaml
beast_skygrid/workflow/rules/rttr.smk
beast_skygrid/workflow/scripts/plotMccTree.R
beast_skygrid/workflow/scripts/plotSkygrid.R
beast_skygrid/workflow/scripts/populate_skygrid_template.py
beast_skygrid/workflow/scripts/prepare_treetime_metadata.py
beast_skygrid/workflow/templates/skygrid.jinja.xml
beast_skygrid-0.6.2.dist-info/METADATA
beast_skygrid-0.6.2.dist-info/WHEEL
beast_skygrid-0.6.2.dist-info/entry_points.txt
beast_skygrid-0.6.2.dist-info/licenses/LICENSE.txt
beast_skygrid-0.6.2.dist-info/RECORD
