Metadata-Version: 2.4
Name: beast-skygrid
Version: 0.6.2
Project-URL: Documentation, https://github.com/wytamma/skygrid#readme
Project-URL: Issues, https://github.com/wytamma/skygrid/issues
Project-URL: Source, https://github.com/wytamma/skygrid
Author-email: Wytamma Wirth <wytamma.wirth@me.com>
License-Expression: MIT
License-File: LICENSE.txt
Classifier: Development Status :: 4 - Beta
Classifier: Programming Language :: Python
Classifier: Programming Language :: Python :: 3.8
Classifier: Programming Language :: Python :: 3.9
Classifier: Programming Language :: Python :: 3.10
Classifier: Programming Language :: Python :: 3.11
Classifier: Programming Language :: Python :: 3.12
Classifier: Programming Language :: Python :: 3.13
Classifier: Programming Language :: Python :: Implementation :: CPython
Classifier: Programming Language :: Python :: Implementation :: PyPy
Requires-Python: >=3.8
Requires-Dist: snk-cli
